odoo9_addon_crm_sale_marketing-9.0.1.0.0.99.dev4-nspkg.pth
odoo_addons/crm_sale_marketing/README.rst
odoo_addons/crm_sale_marketing/__init__.py
odoo_addons/crm_sale_marketing/__openerp__.py
odoo_addons/crm_sale_marketing/i18n/crm_sale_marketing.pot
odoo_addons/crm_sale_marketing/static/description/icon.png
odoo_addons/crm_sale_marketing/views/crm_sale_marketing.xml
odoo9_addon_crm_sale_marketing-9.0.1.0.0.99.dev4.dist-info/METADATA
odoo9_addon_crm_sale_marketing-9.0.1.0.0.99.dev4.dist-info/WHEEL
odoo9_addon_crm_sale_marketing-9.0.1.0.0.99.dev4.dist-info/namespace_packages.txt
odoo9_addon_crm_sale_marketing-9.0.1.0.0.99.dev4.dist-info/top_level.txt
odoo9_addon_crm_sale_marketing-9.0.1.0.0.99.dev4.dist-info/RECORD
